TimeLineClusterPackage/GenericController.py
TimeLineClusterPackage/LogController.py
TimeLineClusterPackage/UtailController.py
TimeLineClusterPackage/__init__.py
TimeLineClusterPackage/config.py
function/__init__.py
function/test_t.py
timelinetesttest13-0.0.dist-info/METADATA
timelinetesttest13-0.0.dist-info/WHEEL
timelinetesttest13-0.0.dist-info/top_level.txt
timelinetesttest13-0.0.dist-info/RECORD
