Metadata-Version: 2.1
Name: timelinetesttest13
Version: 0.0
Summary: This is timelinetestpack0.0.
Home-page: https://github.com/F-Jirayut/create_p
Author: U test
Author-email: fayristh0268@gmail.com
License: MIT
Platform: UNKNOWN
Requires-Python: >=3.6
